odoo/addons/account_invoice_line_sale_line_position/README.rst
odoo/addons/account_invoice_line_sale_line_position/__init__.py
odoo/addons/account_invoice_line_sale_line_position/__manifest__.py
odoo/addons/account_invoice_line_sale_line_position/i18n/account_invoice_line_sale_line_position.pot
odoo/addons/account_invoice_line_sale_line_position/models/__init__.py
odoo/addons/account_invoice_line_sale_line_position/models/account_invoice.py
odoo/addons/account_invoice_line_sale_line_position/readme/CONTRIBUTORS.rst
odoo/addons/account_invoice_line_sale_line_position/readme/DESCRIPTION.rst
odoo/addons/account_invoice_line_sale_line_position/report/invoice_report.xml
odoo/addons/account_invoice_line_sale_line_position/static/description/icon.png
odoo/addons/account_invoice_line_sale_line_position/static/description/index.html
odoo/addons/account_invoice_line_sale_line_position/tests/__init__.py
odoo/addons/account_invoice_line_sale_line_position/tests/test_account_invoice_line_sale_line_position.py
odoo/addons/account_invoice_line_sale_line_position/views/account_move_views.xml
odoo13_addon_account_invoice_line_sale_line_position-13.0.1.0.1.dev4.dist-info/METADATA
odoo13_addon_account_invoice_line_sale_line_position-13.0.1.0.1.dev4.dist-info/WHEEL
odoo13_addon_account_invoice_line_sale_line_position-13.0.1.0.1.dev4.dist-info/top_level.txt
odoo13_addon_account_invoice_line_sale_line_position-13.0.1.0.1.dev4.dist-info/RECORD
