Metadata-Version: 2.1
Name: odoo13-addon-account-invoice-line-sale-line-position
Version: 13.0.1.0.1.dev4
Summary: Adds the related sale line position on invoice line.
Home-page: https://github.com/OCA/account-invoice-reporting
Author: Camptocamp, Odoo Community Association (OCA)
Author-email: support@odoo-community.org
License: AGPL-3
Platform: UNKNOWN
Classifier: Programming Language :: Python
Classifier: Framework :: Odoo
Classifier: Framework :: Odoo :: 13.0
Classifier: License :: OSI Approved :: GNU Affero General Public License v3
Requires-Python: >=3.5
Requires-Dist: odoo13-addon-sale-order-line-position
Requires-Dist: odoo <13.1dev,>=13.0a
